{
  "parent": "minecraft:recipes/root",
  "rewards": {
    "recipes": [
      "medievalworlds:gambeson"
    ]
  },
  "criteria": {
    "leather": {
      "trigger": "minecraft:inventory_changed",
      "conditions": {
        "items": [
          {
            "items": [
              "minecraft:leather"
            ]
          }
        ]
      }
    },
    "wool": {
      "trigger": "minecraft:inventory_changed",
      "conditions": {
        "items": [
          {
            "tag": "minecraft:wool"
          }
        ]
      }
    },
    "has_the_recipe": {
      "trigger": "minecraft:recipe_unlocked",
      "conditions": {
        "recipe": "medievalworlds:gambeson"
      }
    }
  },
  "requirements": [
    [
      "leather",
      "wool",
      "has_the_recipe"
    ]
  ]
}